ckandr/__init__.py
ckandr/ckandr.py
ckandr/coindelta.py
ckandr/coinsecure.py
ckandr/koinex.py
ckandr/main.py
ckandr/unocoin.py
ckandr/utils.py
ckandr/wazirx.py
ckandr/zebpay.py
ckandr-0.3.3.dist-info/METADATA
ckandr-0.3.3.dist-info/RECORD
ckandr-0.3.3.dist-info/WHEEL
ckandr-0.3.3.dist-info/entry_points.txt
ckandr-0.3.3.dist-info/top_level.txt
