Metadata-Version: 2.1
Name: ckandr
Version: 0.3.3
Summary: Cryptocurrency Ka Naya Desi Rate : Cryptocurrency prices from Indian exchanges
Home-page: https://github.com/screwgoth/ckandr
Author: Raseel Bhagat
Author-email: raseelbhagat@gmail.com
License: MIT
Download-URL: https://github.com/screwgoth/ckandr/archive/0.1.tar.gz
Keywords: bitcoin cryptocurrency ticker python cli price-tracker command-line
Platform: UNKNOWN
Classifier: Development Status :: 4 - Beta
Classifier: Environment :: Console
Classifier: Intended Audience :: End Users/Desktop
Classifier: License :: OSI Approved :: MIT License
Classifier: Operating System :: MacOS
Classifier: Operating System :: POSIX
Classifier: Programming Language :: Python
Classifier: Programming Language :: Python :: 3.6
Classifier: Topic :: Utilities
Requires-Dist: certifi (==2017.11.5)
Requires-Dist: chardet (==3.0.4)
Requires-Dist: idna (==2.6)
Requires-Dist: requests (==2.18.4)
Requires-Dist: terminaltables (==3.1.0)
Requires-Dist: urllib3 (==1.22)
